rescore09/__init__.py
rescore09/config.py
rescore09/discordWebhook.py
rescore09/file.py
rescore09/logger.py
rescore09/pass.py
rescore09-1.0.1.dist-info/licenses/LICENSE
rescore09-1.0.1.dist-info/METADATA
rescore09-1.0.1.dist-info/WHEEL
rescore09-1.0.1.dist-info/top_level.txt
rescore09-1.0.1.dist-info/RECORD
