Metadata-Version: 2.4
Name: rescore09
Version: 1.0.1
Summary: My own custom library to help with my projects.
Author-email: rescore09 <admin@rescore.lol>
License: MIT
Project-URL: Homepage, https://github.com/rescore09/rescore
Requires-Python: >=3.7
License-File: LICENSE
Dynamic: license-file
